ratansunpy/.DS_Store
ratansunpy/__init__.py
ratansunpy/client/.DS_Store
ratansunpy/client/__init__.py
ratansunpy/client/client.py
ratansunpy/client/quiet_sun_model.xlsx
ratansunpy/client/quiet_sun_template.xlsx
ratansunpy/core/__init__.py
ratansunpy/core/ar_handling.py
ratansunpy/scrapper/__init__.py
ratansunpy/scrapper/scrapper.py
ratansunpy/time/__init__.py
ratansunpy/time/time.py
ratansunpy/time/timerange.py
ratansunpy/utils/__init__.py
ratansunpy/utils/logger.py
ratansunpy/utils/utils.py
ratansunpy/visualization/__init__.py
ratansunpy/visualization/colormap_files/std_gamma_2.csv
ratansunpy/visualization/colormaps.py
ratansunpy/visualization/visualization.py
ratansunpy-0.2.7.dist-info/LICENSE
ratansunpy-0.2.7.dist-info/METADATA
ratansunpy-0.2.7.dist-info/WHEEL
ratansunpy-0.2.7.dist-info/RECORD
