Metadata-Version: 2.1
Name: ratansunpy
Version: 0.2.7
Summary: RATAN-600 radioastronomical solar data and methods Python library
Home-page: https://github.com/SpbfSAO/RATANSunPy
License: MIT
Keywords: solar physics,radioastronomy,physics,data proccessing,ratan-600
Author: Igor Lysov
Author-email: iilysov.sci@gmail.com
Requires-Python: >=3.10,<4.0
Classifier: License :: OSI Approved :: MIT License
Classifier: Programming Language :: Python :: 3
Classifier: Programming Language :: Python :: 3.10
Classifier: Programming Language :: Python :: 3.11
Classifier: Programming Language :: Python :: 3.12
Requires-Dist: PyWavelets (==1.7.0)
Requires-Dist: astropy (>=6.1.3,<7.0.0)
Requires-Dist: et-xmlfile (>=1.1.0,<2.0.0)
Requires-Dist: matplotlib (>=3.7.0,<4.0.0)
Requires-Dist: numpy (>=1.26.0,<2.0.0)
Requires-Dist: openpyxl (>=3.1.5,<4.0.0)
Requires-Dist: pandas (>=2.2.2,<3.0.0)
Requires-Dist: python-dateutil (>=2.8.2,<3.0.0)
Requires-Dist: requests (>=2.32.3,<3.0.0)
Requires-Dist: scipy (>=1.13.1,<2.0.0)
Requires-Dist: tqdm (>=4.67.1,<5.0.0)
Project-URL: Documentation, https://SpbfSAO.github.io/RATANSunPy/
Project-URL: Repository, https://github.com/SpbfSAO/RATANSunPy
